Metadata-Version: 1.1
Name: dummy-wsgi-framework
Version: 0.0.19
Summary: Dummy WSGI Framework is base for your Web-applications or your own WSGI-framework
Home-page: https://github.com/BorisPlus/dummy_wsgi_framework
Author: BorisPlus
Author-email: boris-plus@mail.ru
License: UNKNOWN
Platform: UNKNOWN
Classifier: Programming Language :: Python :: 3
Classifier: Topic :: Software Development :: Libraries
